pybalboa/__init__.py
pybalboa/__main__.py
pybalboa/client.py
pybalboa/control.py
pybalboa/enums.py
pybalboa/exceptions.py
pybalboa/py.typed
pybalboa/utils.py
pybalboa-1.0.2.dist-info/LICENSE
pybalboa-1.0.2.dist-info/METADATA
pybalboa-1.0.2.dist-info/WHEEL
pybalboa-1.0.2.dist-info/RECORD
