Metadata-Version: 2.1
Name: pybalboa
Version: 1.0.2
Summary: Module to communicate with a Balboa spa wifi adapter.
Home-page: https://github.com/garbled1/pybalboa
Keywords: Balboa,spa,hot tub,asynchronous
Author: Nathan Spencer
Author-email: natekspencer@gmail.com
Requires-Python: >=3.8.1,<4.0.0
Classifier: License :: OSI Approved :: Apache Software License
Classifier: Programming Language :: Python :: 3
Classifier: Programming Language :: Python :: 3.9
Classifier: Programming Language :: Python :: 3.10
Classifier: Programming Language :: Python :: 3.11
Classifier: Programming Language :: Python :: 3.12
Project-URL: Repository, https://github.com/garbled1/pybalboa
